mur/cli.py
mur/adapters/__init__.py
mur/adapters/adapter_factory.py
mur/adapters/base_adapter.py
mur/adapters/private_adapter.py
mur/adapters/public_adapter.py
mur/commands/__init__.py
mur/commands/base.py
mur/commands/build_artifact.py
mur/commands/config_artifacts.py
mur/commands/install_artifacts.py
mur/commands/list_artifacts.py
mur/commands/new_artifact.py
mur/commands/publish_artifact.py
mur/commands/uninstall_artifacts.py
mur/core/__init__.py
mur/core/api_client.py
mur/core/auth.py
mur/core/cache.py
mur/core/capsule_client.py
mur/core/config.py
mur/core/packaging.py
mur/utils/__init__.py
mur/utils/constants.py
mur/utils/error_handler.py
mur/utils/loading.py
mur/utils/models.py
mur-0.0.8.dist-info/METADATA
mur-0.0.8.dist-info/WHEEL
mur-0.0.8.dist-info/entry_points.txt
mur-0.0.8.dist-info/licenses/LICENSE
mur-0.0.8.dist-info/RECORD
